<?xml version="1.0" encoding="utf-8"?>
<savedqueries xmlns:xsi="http://www.w3.org/2001/XMLSchema-instance">
  <savedquery>
    <IsCustomizable>1</IsCustomizable>
    <CanBeDeleted>0</CanBeDeleted>
    <isquickfindquery>0</isquickfindquery>
    <isprivate>0</isprivate>
    <isdefault>1</isdefault>
    <savedqueryid>{e4a5c6d7-47b8-4a16-9037-941eb922be30}</savedqueryid>
    <layoutxml>
      <grid name="resultset" jump="crf46_gig_biometric_att_id" select="1" icon="1" preview="1">
        <row name="result" id="crf46_gig_biometric_attendanceid">
          <cell name="crf46_gig_biometric_att_id" width="300" />
          <cell name="createdon" width="125" />
        </row>
      </grid>
    </layoutxml>
    <querytype>1</querytype>
    <fetchxml>
      <fetch version="1.0" mapping="logical">
        <entity name="crf46_gig_biometric_attendance">
          <attribute name="crf46_gig_biometric_attendanceid" />
          <attribute name="crf46_gig_biometric_att_id" />
          <attribute name="createdon" />
          <order attribute="crf46_gig_biometric_att_id" descending="false" />
        </entity>
      </fetch>
    </fetchxml>
    <IntroducedVersion>1.0</IntroducedVersion>
    <LocalizedNames>
      <LocalizedName description="gig_biometric_attendance Advanced Find View" languagecode="1033" />
    </LocalizedNames>
  </savedquery>
</savedqueries>