<?xml version="1.0" encoding="utf-8"?>
<EntityRelationships xmlns:xsi="http://www.w3.org/2001/XMLSchema-instance">
  <EntityRelationship Name="cr8b3_auto_employee_details_auto_emp_code1_cr8b">
    <EntityRelationshipType>OneToMany</EntityRelationshipType>
    <IsCustomizable>1</IsCustomizable>
    <IntroducedVersion>1.0.0.0</IntroducedVersion>
    <IsHierarchical>0</IsHierarchical>
    <ReferencingEntityName>cr8b3_auto_employee_details</ReferencingEntityName>
    <ReferencedEntityName>cr8b3_gw_Employee_details</ReferencedEntityName>
    <CascadeAssign>NoCascade</CascadeAssign>
    <CascadeDelete>RemoveLink</CascadeDelete>
    <CascadeArchive>RemoveLink</CascadeArchive>
    <CascadeReparent>NoCascade</CascadeReparent>
    <CascadeShare>NoCascade</CascadeShare>
    <CascadeUnshare>NoCascade</CascadeUnshare>
    <CascadeRollupView>NoCascade</CascadeRollupView>
    <IsValidForAdvancedFind>1</IsValidForAdvancedFind>
    <ReferencingAttributeName>cr8b3_auto_emp_code1</ReferencingAttributeName>
    <RelationshipDescription>
      <Descriptions>
        <Description description="" languagecode="1033" />
      </Descriptions>
    </RelationshipDescription>
    <EntityRelationshipRoles>
      <EntityRelationshipRole>
        <NavPaneDisplayOption>UseCollectionName</NavPaneDisplayOption>
        <NavPaneArea>Details</NavPaneArea>
        <NavPaneOrder>10000</NavPaneOrder>
        <NavigationPropertyName>cr8b3_auto_emp_code1</NavigationPropertyName>
        <RelationshipRoleType>1</RelationshipRoleType>
      </EntityRelationshipRole>
      <EntityRelationshipRole>
        <NavigationPropertyName>cr8b3_auto_employee_details_auto_emp_code1_cr8b</NavigationPropertyName>
        <RelationshipRoleType>0</RelationshipRoleType>
      </EntityRelationshipRole>
    </EntityRelationshipRoles>
  </EntityRelationship>
  <EntityRelationship Name="cr8b3_cr8b3_gwia_emp_bank_details_gw_employee_c">
    <EntityRelationshipType>OneToMany</EntityRelationshipType>
    <IsCustomizable>1</IsCustomizable>
    <IntroducedVersion>1.0.0.0</IntroducedVersion>
    <IsHierarchical>0</IsHierarchical>
    <ReferencingEntityName>cr8b3_gwia_Emp_Bank_details</ReferencingEntityName>
    <ReferencedEntityName>cr8b3_gw_Employee_details</ReferencedEntityName>
    <CascadeAssign>NoCascade</CascadeAssign>
    <CascadeDelete>RemoveLink</CascadeDelete>
    <CascadeArchive>RemoveLink</CascadeArchive>
    <CascadeReparent>NoCascade</CascadeReparent>
    <CascadeShare>NoCascade</CascadeShare>
    <CascadeUnshare>NoCascade</CascadeUnshare>
    <CascadeRollupView>NoCascade</CascadeRollupView>
    <IsValidForAdvancedFind>1</IsValidForAdvancedFind>
    <ReferencingAttributeName>cr8b3_gw_employee_code</ReferencingAttributeName>
    <RelationshipDescription>
      <Descriptions>
        <Description description="" languagecode="1033" />
      </Descriptions>
    </RelationshipDescription>
    <EntityRelationshipRoles>
      <EntityRelationshipRole>
        <NavPaneDisplayOption>UseCollectionName</NavPaneDisplayOption>
        <NavPaneArea>Details</NavPaneArea>
        <NavPaneOrder>10000</NavPaneOrder>
        <NavigationPropertyName>cr8b3_gw_employee_code</NavigationPropertyName>
        <RelationshipRoleType>1</RelationshipRoleType>
      </EntityRelationshipRole>
      <EntityRelationshipRole>
        <NavigationPropertyName>cr8b3_cr8b3_gwia_emp_bank_details_gw_employee_c</NavigationPropertyName>
        <RelationshipRoleType>0</RelationshipRoleType>
      </EntityRelationshipRole>
    </EntityRelationshipRoles>
  </EntityRelationship>
  <EntityRelationship Name="cr8b3_cr8b3_gwia_employee_address_details_gw_em">
    <EntityRelationshipType>OneToMany</EntityRelationshipType>
    <IsCustomizable>1</IsCustomizable>
    <IntroducedVersion>1.0.0.0</IntroducedVersion>
    <IsHierarchical>0</IsHierarchical>
    <ReferencingEntityName>cr8b3_gwia_employee_address_details</ReferencingEntityName>
    <ReferencedEntityName>cr8b3_gw_Employee_details</ReferencedEntityName>
    <CascadeAssign>NoCascade</CascadeAssign>
    <CascadeDelete>RemoveLink</CascadeDelete>
    <CascadeArchive>RemoveLink</CascadeArchive>
    <CascadeReparent>NoCascade</CascadeReparent>
    <CascadeShare>NoCascade</CascadeShare>
    <CascadeUnshare>NoCascade</CascadeUnshare>
    <CascadeRollupView>NoCascade</CascadeRollupView>
    <IsValidForAdvancedFind>1</IsValidForAdvancedFind>
    <ReferencingAttributeName>cr8b3_gw_emp_code</ReferencingAttributeName>
    <RelationshipDescription>
      <Descriptions>
        <Description description="" languagecode="1033" />
      </Descriptions>
    </RelationshipDescription>
    <EntityRelationshipRoles>
      <EntityRelationshipRole>
        <NavPaneDisplayOption>UseCollectionName</NavPaneDisplayOption>
        <NavPaneArea>Details</NavPaneArea>
        <NavPaneOrder>10000</NavPaneOrder>
        <NavigationPropertyName>cr8b3_gw_emp_code</NavigationPropertyName>
        <RelationshipRoleType>1</RelationshipRoleType>
      </EntityRelationshipRole>
      <EntityRelationshipRole>
        <NavigationPropertyName>cr8b3_cr8b3_gwia_employee_address_details_gw_em</NavigationPropertyName>
        <RelationshipRoleType>0</RelationshipRoleType>
      </EntityRelationshipRole>
    </EntityRelationshipRoles>
  </EntityRelationship>
  <EntityRelationship Name="cr8b3_cr8b3_gwia_employee_exceptions_gw_emp_id_">
    <EntityRelationshipType>OneToMany</EntityRelationshipType>
    <IsCustomizable>1</IsCustomizable>
    <IntroducedVersion>1.0.0.0</IntroducedVersion>
    <IsHierarchical>0</IsHierarchical>
    <ReferencingEntityName>cr8b3_gwia_employee_exceptions</ReferencingEntityName>
    <ReferencedEntityName>cr8b3_gw_Employee_details</ReferencedEntityName>
    <CascadeAssign>NoCascade</CascadeAssign>
    <CascadeDelete>RemoveLink</CascadeDelete>
    <CascadeArchive>RemoveLink</CascadeArchive>
    <CascadeReparent>NoCascade</CascadeReparent>
    <CascadeShare>NoCascade</CascadeShare>
    <CascadeUnshare>NoCascade</CascadeUnshare>
    <CascadeRollupView>NoCascade</CascadeRollupView>
    <IsValidForAdvancedFind>1</IsValidForAdvancedFind>
    <ReferencingAttributeName>cr8b3_gw_emp_id</ReferencingAttributeName>
    <RelationshipDescription>
      <Descriptions>
        <Description description="" languagecode="1033" />
      </Descriptions>
    </RelationshipDescription>
    <EntityRelationshipRoles>
      <EntityRelationshipRole>
        <NavPaneDisplayOption>UseCollectionName</NavPaneDisplayOption>
        <NavPaneArea>Details</NavPaneArea>
        <NavPaneOrder>10000</NavPaneOrder>
        <NavigationPropertyName>cr8b3_gw_emp_id</NavigationPropertyName>
        <RelationshipRoleType>1</RelationshipRoleType>
      </EntityRelationshipRole>
      <EntityRelationshipRole>
        <NavigationPropertyName>cr8b3_cr8b3_gwia_employee_exceptions_gw_emp_id_</NavigationPropertyName>
        <RelationshipRoleType>0</RelationshipRoleType>
      </EntityRelationshipRole>
    </EntityRelationshipRoles>
  </EntityRelationship>
  <EntityRelationship Name="cr8b3_cr8b3_gwia_employee_salary_details_gw_emp">
    <EntityRelationshipType>OneToMany</EntityRelationshipType>
    <IsCustomizable>1</IsCustomizable>
    <IntroducedVersion>1.0.0.0</IntroducedVersion>
    <IsHierarchical>0</IsHierarchical>
    <ReferencingEntityName>cr8b3_gwia_Employee_Salary_details</ReferencingEntityName>
    <ReferencedEntityName>cr8b3_gw_Employee_details</ReferencedEntityName>
    <CascadeAssign>NoCascade</CascadeAssign>
    <CascadeDelete>RemoveLink</CascadeDelete>
    <CascadeArchive>RemoveLink</CascadeArchive>
    <CascadeReparent>NoCascade</CascadeReparent>
    <CascadeShare>NoCascade</CascadeShare>
    <CascadeUnshare>NoCascade</CascadeUnshare>
    <CascadeRollupView>NoCascade</CascadeRollupView>
    <IsValidForAdvancedFind>1</IsValidForAdvancedFind>
    <ReferencingAttributeName>cr8b3_gw_employee_code</ReferencingAttributeName>
    <RelationshipDescription>
      <Descriptions>
        <Description description="" languagecode="1033" />
      </Descriptions>
    </RelationshipDescription>
    <EntityRelationshipRoles>
      <EntityRelationshipRole>
        <NavPaneDisplayOption>UseCollectionName</NavPaneDisplayOption>
        <NavPaneArea>Details</NavPaneArea>
        <NavPaneOrder>10000</NavPaneOrder>
        <NavigationPropertyName>cr8b3_gw_employee_code</NavigationPropertyName>
        <RelationshipRoleType>1</RelationshipRoleType>
      </EntityRelationshipRole>
      <EntityRelationshipRole>
        <NavigationPropertyName>cr8b3_cr8b3_gwia_employee_salary_details_gw_emp</NavigationPropertyName>
        <RelationshipRoleType>0</RelationshipRoleType>
      </EntityRelationshipRole>
    </EntityRelationshipRoles>
  </EntityRelationship>
  <EntityRelationship Name="cr8b3_cr8b3_gwia_employee_teramind_report_Emplo">
    <EntityRelationshipType>OneToMany</EntityRelationshipType>
    <IsCustomizable>1</IsCustomizable>
    <IntroducedVersion>1.0.0.0</IntroducedVersion>
    <IsHierarchical>0</IsHierarchical>
    <ReferencingEntityName>cr8b3_gwia_employee_teramind_report</ReferencingEntityName>
    <ReferencedEntityName>cr8b3_gw_Employee_details</ReferencedEntityName>
    <CascadeAssign>NoCascade</CascadeAssign>
    <CascadeDelete>RemoveLink</CascadeDelete>
    <CascadeArchive>RemoveLink</CascadeArchive>
    <CascadeReparent>NoCascade</CascadeReparent>
    <CascadeShare>NoCascade</CascadeShare>
    <CascadeUnshare>NoCascade</CascadeUnshare>
    <CascadeRollupView>NoCascade</CascadeRollupView>
    <IsValidForAdvancedFind>1</IsValidForAdvancedFind>
    <ReferencingAttributeName>cr8b3_Employee_number</ReferencingAttributeName>
    <RelationshipDescription>
      <Descriptions>
        <Description description="" languagecode="1033" />
      </Descriptions>
    </RelationshipDescription>
    <EntityRelationshipRoles>
      <EntityRelationshipRole>
        <NavPaneDisplayOption>UseCollectionName</NavPaneDisplayOption>
        <NavPaneArea>Details</NavPaneArea>
        <NavPaneOrder>10000</NavPaneOrder>
        <NavigationPropertyName>cr8b3_Employee_number</NavigationPropertyName>
        <RelationshipRoleType>1</RelationshipRoleType>
      </EntityRelationshipRole>
      <EntityRelationshipRole>
        <NavigationPropertyName>cr8b3_cr8b3_gwia_employee_teramind_report_Emplo</NavigationPropertyName>
        <RelationshipRoleType>0</RelationshipRoleType>
      </EntityRelationshipRole>
    </EntityRelationshipRoles>
  </EntityRelationship>
  <EntityRelationship Name="cr8b3_cr8b3_gwia_salary_increment_gw_employee_i">
    <EntityRelationshipType>OneToMany</EntityRelationshipType>
    <IsCustomizable>1</IsCustomizable>
    <IntroducedVersion>1.0.0.0</IntroducedVersion>
    <IsHierarchical>0</IsHierarchical>
    <ReferencingEntityName>cr8b3_gwia_salary_increment</ReferencingEntityName>
    <ReferencedEntityName>cr8b3_gw_Employee_details</ReferencedEntityName>
    <CascadeAssign>NoCascade</CascadeAssign>
    <CascadeDelete>RemoveLink</CascadeDelete>
    <CascadeArchive>RemoveLink</CascadeArchive>
    <CascadeReparent>NoCascade</CascadeReparent>
    <CascadeShare>NoCascade</CascadeShare>
    <CascadeUnshare>NoCascade</CascadeUnshare>
    <CascadeRollupView>NoCascade</CascadeRollupView>
    <IsValidForAdvancedFind>1</IsValidForAdvancedFind>
    <ReferencingAttributeName>cr8b3_gw_employee_id</ReferencingAttributeName>
    <RelationshipDescription>
      <Descriptions>
        <Description description="" languagecode="1033" />
      </Descriptions>
    </RelationshipDescription>
    <EntityRelationshipRoles>
      <EntityRelationshipRole>
        <NavPaneDisplayOption>UseCollectionName</NavPaneDisplayOption>
        <NavPaneArea>Details</NavPaneArea>
        <NavPaneOrder>10000</NavPaneOrder>
        <NavigationPropertyName>cr8b3_gw_employee_id</NavigationPropertyName>
        <RelationshipRoleType>1</RelationshipRoleType>
      </EntityRelationshipRole>
      <EntityRelationshipRole>
        <NavigationPropertyName>cr8b3_cr8b3_gwia_salary_increment_gw_employee_i</NavigationPropertyName>
        <RelationshipRoleType>0</RelationshipRoleType>
      </EntityRelationshipRole>
    </EntityRelationshipRoles>
  </EntityRelationship>
  <EntityRelationship Name="cr8b3_cr8b3_gwia_teramind_report_gw_employee_Id">
    <EntityRelationshipType>OneToMany</EntityRelationshipType>
    <IsCustomizable>1</IsCustomizable>
    <IntroducedVersion>1.0.0.0</IntroducedVersion>
    <IsHierarchical>0</IsHierarchical>
    <ReferencingEntityName>cr8b3_gwia_Teramind_Report</ReferencingEntityName>
    <ReferencedEntityName>cr8b3_gw_Employee_details</ReferencedEntityName>
    <CascadeAssign>NoCascade</CascadeAssign>
    <CascadeDelete>RemoveLink</CascadeDelete>
    <CascadeArchive>RemoveLink</CascadeArchive>
    <CascadeReparent>NoCascade</CascadeReparent>
    <CascadeShare>NoCascade</CascadeShare>
    <CascadeUnshare>NoCascade</CascadeUnshare>
    <CascadeRollupView>NoCascade</CascadeRollupView>
    <IsValidForAdvancedFind>1</IsValidForAdvancedFind>
    <ReferencingAttributeName>cr8b3_gw_employee_Id</ReferencingAttributeName>
    <RelationshipDescription>
      <Descriptions>
        <Description description="" languagecode="1033" />
      </Descriptions>
    </RelationshipDescription>
    <EntityRelationshipRoles>
      <EntityRelationshipRole>
        <NavPaneDisplayOption>UseCollectionName</NavPaneDisplayOption>
        <NavPaneArea>Details</NavPaneArea>
        <NavPaneOrder>10000</NavPaneOrder>
        <NavigationPropertyName>cr8b3_gw_employee_Id</NavigationPropertyName>
        <RelationshipRoleType>1</RelationshipRoleType>
      </EntityRelationshipRole>
      <EntityRelationshipRole>
        <NavigationPropertyName>cr8b3_cr8b3_gwia_teramind_report_gw_employee_Id</NavigationPropertyName>
        <RelationshipRoleType>0</RelationshipRoleType>
      </EntityRelationshipRole>
    </EntityRelationshipRoles>
  </EntityRelationship>
  <EntityRelationship Name="cr8b3_gwia_employee_interaction_gw_employee_cod">
    <EntityRelationshipType>OneToMany</EntityRelationshipType>
    <IsCustomizable>1</IsCustomizable>
    <IntroducedVersion>1.0.0.0</IntroducedVersion>
    <IsHierarchical>0</IsHierarchical>
    <ReferencingEntityName>cr8b3_gwia_employee_interaction</ReferencingEntityName>
    <ReferencedEntityName>cr8b3_gw_Employee_details</ReferencedEntityName>
    <CascadeAssign>NoCascade</CascadeAssign>
    <CascadeDelete>RemoveLink</CascadeDelete>
    <CascadeArchive>RemoveLink</CascadeArchive>
    <CascadeReparent>NoCascade</CascadeReparent>
    <CascadeShare>NoCascade</CascadeShare>
    <CascadeUnshare>NoCascade</CascadeUnshare>
    <CascadeRollupView>NoCascade</CascadeRollupView>
    <IsValidForAdvancedFind>1</IsValidForAdvancedFind>
    <ReferencingAttributeName>cr8b3_gw_employee_code</ReferencingAttributeName>
    <RelationshipDescription>
      <Descriptions>
        <Description description="" languagecode="1033" />
      </Descriptions>
    </RelationshipDescription>
    <EntityRelationshipRoles>
      <EntityRelationshipRole>
        <NavPaneDisplayOption>UseCollectionName</NavPaneDisplayOption>
        <NavPaneArea>Details</NavPaneArea>
        <NavPaneOrder>10000</NavPaneOrder>
        <NavigationPropertyName>cr8b3_gw_employee_code</NavigationPropertyName>
        <RelationshipRoleType>1</RelationshipRoleType>
      </EntityRelationshipRole>
      <EntityRelationshipRole>
        <NavigationPropertyName>cr8b3_gwia_employee_interaction_gw_employee_cod</NavigationPropertyName>
        <RelationshipRoleType>0</RelationshipRoleType>
      </EntityRelationshipRole>
    </EntityRelationshipRoles>
  </EntityRelationship>
  <EntityRelationship Name="cr8b3_gwia_employee_log_management_gw_employee_">
    <EntityRelationshipType>OneToMany</EntityRelationshipType>
    <IsCustomizable>1</IsCustomizable>
    <IntroducedVersion>1.0.0.0</IntroducedVersion>
    <IsHierarchical>0</IsHierarchical>
    <ReferencingEntityName>cr8b3_gwia_employee_log_management</ReferencingEntityName>
    <ReferencedEntityName>cr8b3_gw_Employee_details</ReferencedEntityName>
    <CascadeAssign>NoCascade</CascadeAssign>
    <CascadeDelete>RemoveLink</CascadeDelete>
    <CascadeArchive>RemoveLink</CascadeArchive>
    <CascadeReparent>NoCascade</CascadeReparent>
    <CascadeShare>NoCascade</CascadeShare>
    <CascadeUnshare>NoCascade</CascadeUnshare>
    <CascadeRollupView>NoCascade</CascadeRollupView>
    <IsValidForAdvancedFind>1</IsValidForAdvancedFind>
    <ReferencingAttributeName>cr8b3_gw_employee_code</ReferencingAttributeName>
    <RelationshipDescription>
      <Descriptions>
        <Description description="" languagecode="1033" />
      </Descriptions>
    </RelationshipDescription>
    <EntityRelationshipRoles>
      <EntityRelationshipRole>
        <NavPaneDisplayOption>UseCollectionName</NavPaneDisplayOption>
        <NavPaneArea>Details</NavPaneArea>
        <NavPaneOrder>10000</NavPaneOrder>
        <NavigationPropertyName>cr8b3_gw_employee_code</NavigationPropertyName>
        <RelationshipRoleType>1</RelationshipRoleType>
      </EntityRelationshipRole>
      <EntityRelationshipRole>
        <NavigationPropertyName>cr8b3_gwia_employee_log_management_gw_employee_</NavigationPropertyName>
        <RelationshipRoleType>0</RelationshipRoleType>
      </EntityRelationshipRole>
    </EntityRelationshipRoles>
  </EntityRelationship>
  <EntityRelationship Name="cr8b3_gwia_it_audit_gw_employee_code_cr8b3_gw_e">
    <EntityRelationshipType>OneToMany</EntityRelationshipType>
    <IsCustomizable>1</IsCustomizable>
    <IntroducedVersion>1.0.0.0</IntroducedVersion>
    <IsHierarchical>0</IsHierarchical>
    <ReferencingEntityName>cr8b3_gwia_it_audit</ReferencingEntityName>
    <ReferencedEntityName>cr8b3_gw_Employee_details</ReferencedEntityName>
    <CascadeAssign>NoCascade</CascadeAssign>
    <CascadeDelete>RemoveLink</CascadeDelete>
    <CascadeArchive>RemoveLink</CascadeArchive>
    <CascadeReparent>NoCascade</CascadeReparent>
    <CascadeShare>NoCascade</CascadeShare>
    <CascadeUnshare>NoCascade</CascadeUnshare>
    <CascadeRollupView>NoCascade</CascadeRollupView>
    <IsValidForAdvancedFind>1</IsValidForAdvancedFind>
    <ReferencingAttributeName>cr8b3_gw_employee_code</ReferencingAttributeName>
    <RelationshipDescription>
      <Descriptions>
        <Description description="" languagecode="1033" />
      </Descriptions>
    </RelationshipDescription>
    <EntityRelationshipRoles>
      <EntityRelationshipRole>
        <NavPaneDisplayOption>UseCollectionName</NavPaneDisplayOption>
        <NavPaneArea>Details</NavPaneArea>
        <NavPaneOrder>10000</NavPaneOrder>
        <NavigationPropertyName>cr8b3_gw_employee_code</NavigationPropertyName>
        <RelationshipRoleType>1</RelationshipRoleType>
      </EntityRelationshipRole>
      <EntityRelationshipRole>
        <NavigationPropertyName>cr8b3_gwia_it_audit_gw_employee_code_cr8b3_gw_e</NavigationPropertyName>
        <RelationshipRoleType>0</RelationshipRoleType>
      </EntityRelationshipRole>
    </EntityRelationshipRoles>
  </EntityRelationship>
  <EntityRelationship Name="cr8b3_gwia_variable_pay_gw_employee_code_cr8b3_">
    <EntityRelationshipType>OneToMany</EntityRelationshipType>
    <IsCustomizable>1</IsCustomizable>
    <IntroducedVersion>1.0.0.0</IntroducedVersion>
    <IsHierarchical>0</IsHierarchical>
    <ReferencingEntityName>cr8b3_gwia_variable_pay</ReferencingEntityName>
    <ReferencedEntityName>cr8b3_gw_Employee_details</ReferencedEntityName>
    <CascadeAssign>NoCascade</CascadeAssign>
    <CascadeDelete>RemoveLink</CascadeDelete>
    <CascadeArchive>RemoveLink</CascadeArchive>
    <CascadeReparent>NoCascade</CascadeReparent>
    <CascadeShare>NoCascade</CascadeShare>
    <CascadeUnshare>NoCascade</CascadeUnshare>
    <CascadeRollupView>NoCascade</CascadeRollupView>
    <IsValidForAdvancedFind>1</IsValidForAdvancedFind>
    <ReferencingAttributeName>cr8b3_gw_employee_code</ReferencingAttributeName>
    <RelationshipDescription>
      <Descriptions>
        <Description description="" languagecode="1033" />
      </Descriptions>
    </RelationshipDescription>
    <EntityRelationshipRoles>
      <EntityRelationshipRole>
        <NavPaneDisplayOption>UseCollectionName</NavPaneDisplayOption>
        <NavPaneArea>Details</NavPaneArea>
        <NavPaneOrder>10000</NavPaneOrder>
        <NavigationPropertyName>cr8b3_gw_employee_code</NavigationPropertyName>
        <RelationshipRoleType>1</RelationshipRoleType>
      </EntityRelationshipRole>
      <EntityRelationshipRole>
        <NavigationPropertyName>cr8b3_gwia_variable_pay_gw_employee_code_cr8b3_</NavigationPropertyName>
        <RelationshipRoleType>0</RelationshipRoleType>
      </EntityRelationshipRole>
    </EntityRelationshipRoles>
  </EntityRelationship>
  <EntityRelationship Name="crf46_auto_incentive_details_gw_employee_code_cr8b3_gw_employee_details">
    <EntityRelationshipType>OneToMany</EntityRelationshipType>
    <IsCustomizable>1</IsCustomizable>
    <IntroducedVersion>1.0.0.0</IntroducedVersion>
    <IsHierarchical>0</IsHierarchical>
    <ReferencingEntityName>crf46_auto_incentive_details</ReferencingEntityName>
    <ReferencedEntityName>cr8b3_gw_Employee_details</ReferencedEntityName>
    <CascadeAssign>NoCascade</CascadeAssign>
    <CascadeDelete>RemoveLink</CascadeDelete>
    <CascadeArchive>RemoveLink</CascadeArchive>
    <CascadeReparent>NoCascade</CascadeReparent>
    <CascadeShare>NoCascade</CascadeShare>
    <CascadeUnshare>NoCascade</CascadeUnshare>
    <CascadeRollupView>NoCascade</CascadeRollupView>
    <IsValidForAdvancedFind>1</IsValidForAdvancedFind>
    <ReferencingAttributeName>crf46_gw_employee_code</ReferencingAttributeName>
    <RelationshipDescription>
      <Descriptions>
        <Description description="" languagecode="1033" />
      </Descriptions>
    </RelationshipDescription>
    <EntityRelationshipRoles>
      <EntityRelationshipRole>
        <NavPaneDisplayOption>UseCollectionName</NavPaneDisplayOption>
        <NavPaneArea>Details</NavPaneArea>
        <NavPaneOrder>10000</NavPaneOrder>
        <NavigationPropertyName>crf46_gw_employee_code</NavigationPropertyName>
        <RelationshipRoleType>1</RelationshipRoleType>
      </EntityRelationshipRole>
      <EntityRelationshipRole>
        <NavigationPropertyName>crf46_auto_incentive_details_gw_employee_code_cr8b3_gw_employee_details</NavigationPropertyName>
        <RelationshipRoleType>0</RelationshipRoleType>
      </EntityRelationshipRole>
    </EntityRelationshipRoles>
  </EntityRelationship>
  <EntityRelationship Name="crf46_cr8b3_gw_employee_details_gw_emp_reporting_manager_cr8b3_gw_employee_details">
    <EntityRelationshipType>OneToMany</EntityRelationshipType>
    <IsCustomizable>1</IsCustomizable>
    <IntroducedVersion>1.0.0.0</IntroducedVersion>
    <IsHierarchical>0</IsHierarchical>
    <ReferencingEntityName>cr8b3_gw_Employee_details</ReferencingEntityName>
    <ReferencedEntityName>cr8b3_gw_Employee_details</ReferencedEntityName>
    <CascadeAssign>NoCascade</CascadeAssign>
    <CascadeDelete>RemoveLink</CascadeDelete>
    <CascadeArchive>RemoveLink</CascadeArchive>
    <CascadeReparent>NoCascade</CascadeReparent>
    <CascadeShare>NoCascade</CascadeShare>
    <CascadeUnshare>NoCascade</CascadeUnshare>
    <CascadeRollupView>NoCascade</CascadeRollupView>
    <IsValidForAdvancedFind>1</IsValidForAdvancedFind>
    <ReferencingAttributeName>crf46_gw_emp_reporting_manager</ReferencingAttributeName>
    <RelationshipDescription>
      <Descriptions>
        <Description description="" languagecode="1033" />
      </Descriptions>
    </RelationshipDescription>
    <EntityRelationshipRoles>
      <EntityRelationshipRole>
        <NavPaneDisplayOption>UseCollectionName</NavPaneDisplayOption>
        <NavPaneArea>Details</NavPaneArea>
        <NavPaneOrder>10000</NavPaneOrder>
        <NavigationPropertyName>crf46_gw_emp_reporting_manager</NavigationPropertyName>
        <RelationshipRoleType>1</RelationshipRoleType>
      </EntityRelationshipRole>
      <EntityRelationshipRole>
        <NavigationPropertyName>crf46_cr8b3_gw_employee_details_gw_emp_reporting_manager_cr8b3_gw_employee_details</NavigationPropertyName>
        <RelationshipRoleType>0</RelationshipRoleType>
      </EntityRelationshipRole>
    </EntityRelationshipRoles>
  </EntityRelationship>
  <EntityRelationship Name="crf46_gig_appraisal_forms_gig_employee_id_cr8b3_gw_employee_details">
    <EntityRelationshipType>OneToMany</EntityRelationshipType>
    <IsCustomizable>1</IsCustomizable>
    <IntroducedVersion>1.0.0.0</IntroducedVersion>
    <IsHierarchical>0</IsHierarchical>
    <ReferencingEntityName>crf46_gig_appraisal_forms</ReferencingEntityName>
    <ReferencedEntityName>cr8b3_gw_Employee_details</ReferencedEntityName>
    <CascadeAssign>NoCascade</CascadeAssign>
    <CascadeDelete>RemoveLink</CascadeDelete>
    <CascadeArchive>RemoveLink</CascadeArchive>
    <CascadeReparent>NoCascade</CascadeReparent>
    <CascadeShare>NoCascade</CascadeShare>
    <CascadeUnshare>NoCascade</CascadeUnshare>
    <CascadeRollupView>NoCascade</CascadeRollupView>
    <IsValidForAdvancedFind>1</IsValidForAdvancedFind>
    <ReferencingAttributeName>crf46_gig_employee_id</ReferencingAttributeName>
    <RelationshipDescription>
      <Descriptions>
        <Description description="" languagecode="1033" />
      </Descriptions>
    </RelationshipDescription>
    <EntityRelationshipRoles>
      <EntityRelationshipRole>
        <NavPaneDisplayOption>UseCollectionName</NavPaneDisplayOption>
        <NavPaneArea>Details</NavPaneArea>
        <NavPaneOrder>10000</NavPaneOrder>
        <NavigationPropertyName>crf46_gig_employee_id</NavigationPropertyName>
        <RelationshipRoleType>1</RelationshipRoleType>
      </EntityRelationshipRole>
      <EntityRelationshipRole>
        <NavigationPropertyName>crf46_gig_appraisal_forms_gig_employee_id_cr8b3_gw_employee_details</NavigationPropertyName>
        <RelationshipRoleType>0</RelationshipRoleType>
      </EntityRelationshipRole>
    </EntityRelationshipRoles>
  </EntityRelationship>
  <EntityRelationship Name="crf46_gig_biometric_attendance_gig_employee_code_cr8b3_gw_employee_details">
    <EntityRelationshipType>OneToMany</EntityRelationshipType>
    <IsCustomizable>1</IsCustomizable>
    <IntroducedVersion>1.0.0.0</IntroducedVersion>
    <IsHierarchical>0</IsHierarchical>
    <ReferencingEntityName>crf46_gig_biometric_attendance</ReferencingEntityName>
    <ReferencedEntityName>cr8b3_gw_Employee_details</ReferencedEntityName>
    <CascadeAssign>NoCascade</CascadeAssign>
    <CascadeDelete>RemoveLink</CascadeDelete>
    <CascadeArchive>RemoveLink</CascadeArchive>
    <CascadeReparent>NoCascade</CascadeReparent>
    <CascadeShare>NoCascade</CascadeShare>
    <CascadeUnshare>NoCascade</CascadeUnshare>
    <CascadeRollupView>NoCascade</CascadeRollupView>
    <IsValidForAdvancedFind>1</IsValidForAdvancedFind>
    <ReferencingAttributeName>crf46_gig_employee_code</ReferencingAttributeName>
    <RelationshipDescription>
      <Descriptions>
        <Description description="" languagecode="1033" />
      </Descriptions>
    </RelationshipDescription>
    <EntityRelationshipRoles>
      <EntityRelationshipRole>
        <NavPaneDisplayOption>UseCollectionName</NavPaneDisplayOption>
        <NavPaneArea>Details</NavPaneArea>
        <NavPaneOrder>10000</NavPaneOrder>
        <NavigationPropertyName>crf46_gig_employee_code</NavigationPropertyName>
        <RelationshipRoleType>1</RelationshipRoleType>
      </EntityRelationshipRole>
      <EntityRelationshipRole>
        <NavigationPropertyName>crf46_gig_biometric_attendance_gig_employee_code_cr8b3_gw_employee_details</NavigationPropertyName>
        <RelationshipRoleType>0</RelationshipRoleType>
      </EntityRelationshipRole>
    </EntityRelationshipRoles>
  </EntityRelationship>
  <EntityRelationship Name="crf46_gig_biometric_exceptions_gig_employee_code_cr8b3_gw_employee_details">
    <EntityRelationshipType>OneToMany</EntityRelationshipType>
    <IsCustomizable>1</IsCustomizable>
    <IntroducedVersion>1.0.0.0</IntroducedVersion>
    <IsHierarchical>0</IsHierarchical>
    <ReferencingEntityName>crf46_gig_biometric_exceptions</ReferencingEntityName>
    <ReferencedEntityName>cr8b3_gw_Employee_details</ReferencedEntityName>
    <CascadeAssign>NoCascade</CascadeAssign>
    <CascadeDelete>RemoveLink</CascadeDelete>
    <CascadeArchive>RemoveLink</CascadeArchive>
    <CascadeReparent>NoCascade</CascadeReparent>
    <CascadeShare>NoCascade</CascadeShare>
    <CascadeUnshare>NoCascade</CascadeUnshare>
    <CascadeRollupView>NoCascade</CascadeRollupView>
    <IsValidForAdvancedFind>1</IsValidForAdvancedFind>
    <ReferencingAttributeName>crf46_gig_employee_code</ReferencingAttributeName>
    <RelationshipDescription>
      <Descriptions>
        <Description description="" languagecode="1033" />
      </Descriptions>
    </RelationshipDescription>
    <EntityRelationshipRoles>
      <EntityRelationshipRole>
        <NavPaneDisplayOption>UseCollectionName</NavPaneDisplayOption>
        <NavPaneArea>Details</NavPaneArea>
        <NavPaneOrder>10000</NavPaneOrder>
        <NavigationPropertyName>crf46_gig_employee_code</NavigationPropertyName>
        <RelationshipRoleType>1</RelationshipRoleType>
      </EntityRelationshipRole>
      <EntityRelationshipRole>
        <NavigationPropertyName>crf46_gig_biometric_exceptions_gig_employee_code_cr8b3_gw_employee_details</NavigationPropertyName>
        <RelationshipRoleType>0</RelationshipRoleType>
      </EntityRelationshipRole>
    </EntityRelationshipRoles>
  </EntityRelationship>
  <EntityRelationship Name="crf46_gig_data_update_requests_gig_employee_code_cr8b3_gw_employee_details">
    <EntityRelationshipType>OneToMany</EntityRelationshipType>
    <IsCustomizable>1</IsCustomizable>
    <IntroducedVersion>1.0.0.0</IntroducedVersion>
    <IsHierarchical>0</IsHierarchical>
    <ReferencingEntityName>crf46_gig_data_update_requests</ReferencingEntityName>
    <ReferencedEntityName>cr8b3_gw_Employee_details</ReferencedEntityName>
    <CascadeAssign>NoCascade</CascadeAssign>
    <CascadeDelete>RemoveLink</CascadeDelete>
    <CascadeArchive>RemoveLink</CascadeArchive>
    <CascadeReparent>NoCascade</CascadeReparent>
    <CascadeShare>NoCascade</CascadeShare>
    <CascadeUnshare>NoCascade</CascadeUnshare>
    <CascadeRollupView>NoCascade</CascadeRollupView>
    <IsValidForAdvancedFind>1</IsValidForAdvancedFind>
    <ReferencingAttributeName>crf46_gig_employee_code</ReferencingAttributeName>
    <RelationshipDescription>
      <Descriptions>
        <Description description="" languagecode="1033" />
      </Descriptions>
    </RelationshipDescription>
    <EntityRelationshipRoles>
      <EntityRelationshipRole>
        <NavPaneDisplayOption>UseCollectionName</NavPaneDisplayOption>
        <NavPaneArea>Details</NavPaneArea>
        <NavPaneOrder>10000</NavPaneOrder>
        <NavigationPropertyName>crf46_gig_employee_code</NavigationPropertyName>
        <RelationshipRoleType>1</RelationshipRoleType>
      </EntityRelationshipRole>
      <EntityRelationshipRole>
        <NavigationPropertyName>crf46_gig_data_update_requests_gig_employee_code_cr8b3_gw_employee_details</NavigationPropertyName>
        <RelationshipRoleType>0</RelationshipRoleType>
      </EntityRelationshipRole>
    </EntityRelationshipRoles>
  </EntityRelationship>
  <EntityRelationship Name="crf46_gig_emp_plusminus_gig_employee_id_cr8b3_gw_employee_details">
    <EntityRelationshipType>OneToMany</EntityRelationshipType>
    <IsCustomizable>1</IsCustomizable>
    <IntroducedVersion>1.0.0.0</IntroducedVersion>
    <IsHierarchical>0</IsHierarchical>
    <ReferencingEntityName>crf46_gig_emp_plusminus</ReferencingEntityName>
    <ReferencedEntityName>cr8b3_gw_Employee_details</ReferencedEntityName>
    <CascadeAssign>NoCascade</CascadeAssign>
    <CascadeDelete>RemoveLink</CascadeDelete>
    <CascadeArchive>RemoveLink</CascadeArchive>
    <CascadeReparent>NoCascade</CascadeReparent>
    <CascadeShare>NoCascade</CascadeShare>
    <CascadeUnshare>NoCascade</CascadeUnshare>
    <CascadeRollupView>NoCascade</CascadeRollupView>
    <IsValidForAdvancedFind>1</IsValidForAdvancedFind>
    <ReferencingAttributeName>crf46_gig_employee_id</ReferencingAttributeName>
    <RelationshipDescription>
      <Descriptions>
        <Description description="" languagecode="1033" />
      </Descriptions>
    </RelationshipDescription>
    <EntityRelationshipRoles>
      <EntityRelationshipRole>
        <NavPaneDisplayOption>UseCollectionName</NavPaneDisplayOption>
        <NavPaneArea>Details</NavPaneArea>
        <NavPaneOrder>10000</NavPaneOrder>
        <NavigationPropertyName>crf46_gig_employee_id</NavigationPropertyName>
        <RelationshipRoleType>1</RelationshipRoleType>
      </EntityRelationshipRole>
      <EntityRelationshipRole>
        <NavigationPropertyName>crf46_gig_emp_plusminus_gig_employee_id_cr8b3_gw_employee_details</NavigationPropertyName>
        <RelationshipRoleType>0</RelationshipRoleType>
      </EntityRelationshipRole>
    </EntityRelationshipRoles>
  </EntityRelationship>
  <EntityRelationship Name="crf46_gig_employee_address_details_gig_employee_code_cr8b3_gw_employee_details">
    <EntityRelationshipType>OneToMany</EntityRelationshipType>
    <IsCustomizable>1</IsCustomizable>
    <IntroducedVersion>1.0.0.0</IntroducedVersion>
    <IsHierarchical>0</IsHierarchical>
    <ReferencingEntityName>crf46_gig_employee_address_details</ReferencingEntityName>
    <ReferencedEntityName>cr8b3_gw_Employee_details</ReferencedEntityName>
    <CascadeAssign>NoCascade</CascadeAssign>
    <CascadeDelete>RemoveLink</CascadeDelete>
    <CascadeArchive>RemoveLink</CascadeArchive>
    <CascadeReparent>NoCascade</CascadeReparent>
    <CascadeShare>NoCascade</CascadeShare>
    <CascadeUnshare>NoCascade</CascadeUnshare>
    <CascadeRollupView>NoCascade</CascadeRollupView>
    <IsValidForAdvancedFind>1</IsValidForAdvancedFind>
    <ReferencingAttributeName>crf46_gig_employee_code</ReferencingAttributeName>
    <RelationshipDescription>
      <Descriptions>
        <Description description="" languagecode="1033" />
      </Descriptions>
    </RelationshipDescription>
    <EntityRelationshipRoles>
      <EntityRelationshipRole>
        <NavPaneDisplayOption>UseCollectionName</NavPaneDisplayOption>
        <NavPaneArea>Details</NavPaneArea>
        <NavPaneOrder>10000</NavPaneOrder>
        <NavigationPropertyName>crf46_gig_employee_code</NavigationPropertyName>
        <RelationshipRoleType>1</RelationshipRoleType>
      </EntityRelationshipRole>
      <EntityRelationshipRole>
        <NavigationPropertyName>crf46_gig_employee_address_details_gig_employee_code_cr8b3_gw_employee_details</NavigationPropertyName>
        <RelationshipRoleType>0</RelationshipRoleType>
      </EntityRelationshipRole>
    </EntityRelationshipRoles>
  </EntityRelationship>
  <EntityRelationship Name="crf46_gig_employee_bank_details_gig_employee_code_cr8b3_gw_employee_details">
    <EntityRelationshipType>OneToMany</EntityRelationshipType>
    <IsCustomizable>1</IsCustomizable>
    <IntroducedVersion>1.0.0.0</IntroducedVersion>
    <IsHierarchical>0</IsHierarchical>
    <ReferencingEntityName>crf46_gig_employee_bank_details</ReferencingEntityName>
    <ReferencedEntityName>cr8b3_gw_Employee_details</ReferencedEntityName>
    <CascadeAssign>NoCascade</CascadeAssign>
    <CascadeDelete>RemoveLink</CascadeDelete>
    <CascadeArchive>RemoveLink</CascadeArchive>
    <CascadeReparent>NoCascade</CascadeReparent>
    <CascadeShare>NoCascade</CascadeShare>
    <CascadeUnshare>NoCascade</CascadeUnshare>
    <CascadeRollupView>NoCascade</CascadeRollupView>
    <IsValidForAdvancedFind>1</IsValidForAdvancedFind>
    <ReferencingAttributeName>crf46_gig_employee_code</ReferencingAttributeName>
    <RelationshipDescription>
      <Descriptions>
        <Description description="" languagecode="1033" />
      </Descriptions>
    </RelationshipDescription>
    <EntityRelationshipRoles>
      <EntityRelationshipRole>
        <NavPaneDisplayOption>UseCollectionName</NavPaneDisplayOption>
        <NavPaneArea>Details</NavPaneArea>
        <NavPaneOrder>10000</NavPaneOrder>
        <NavigationPropertyName>crf46_gig_employee_code</NavigationPropertyName>
        <RelationshipRoleType>1</RelationshipRoleType>
      </EntityRelationshipRole>
      <EntityRelationshipRole>
        <NavigationPropertyName>crf46_gig_employee_bank_details_gig_employee_code_cr8b3_gw_employee_details</NavigationPropertyName>
        <RelationshipRoleType>0</RelationshipRoleType>
      </EntityRelationshipRole>
    </EntityRelationshipRoles>
  </EntityRelationship>
  <EntityRelationship Name="crf46_gig_employee_bgv_gig_bgv_employee_code_cr8b3_gw_employee_details">
    <EntityRelationshipType>OneToMany</EntityRelationshipType>
    <IsCustomizable>1</IsCustomizable>
    <IntroducedVersion>1.0.0.0</IntroducedVersion>
    <IsHierarchical>0</IsHierarchical>
    <ReferencingEntityName>crf46_gig_employee_bgv</ReferencingEntityName>
    <ReferencedEntityName>cr8b3_gw_Employee_details</ReferencedEntityName>
    <CascadeAssign>NoCascade</CascadeAssign>
    <CascadeDelete>RemoveLink</CascadeDelete>
    <CascadeArchive>RemoveLink</CascadeArchive>
    <CascadeReparent>NoCascade</CascadeReparent>
    <CascadeShare>NoCascade</CascadeShare>
    <CascadeUnshare>NoCascade</CascadeUnshare>
    <CascadeRollupView>NoCascade</CascadeRollupView>
    <IsValidForAdvancedFind>1</IsValidForAdvancedFind>
    <ReferencingAttributeName>crf46_gig_bgv_employee_code</ReferencingAttributeName>
    <RelationshipDescription>
      <Descriptions>
        <Description description="" languagecode="1033" />
      </Descriptions>
    </RelationshipDescription>
    <EntityRelationshipRoles>
      <EntityRelationshipRole>
        <NavPaneDisplayOption>UseCollectionName</NavPaneDisplayOption>
        <NavPaneArea>Details</NavPaneArea>
        <NavPaneOrder>10000</NavPaneOrder>
        <NavigationPropertyName>crf46_gig_bgv_employee_code</NavigationPropertyName>
        <RelationshipRoleType>1</RelationshipRoleType>
      </EntityRelationshipRole>
      <EntityRelationshipRole>
        <NavigationPropertyName>crf46_gig_employee_bgv_gig_bgv_employee_code_cr8b3_gw_employee_details</NavigationPropertyName>
        <RelationshipRoleType>0</RelationshipRoleType>
      </EntityRelationshipRole>
    </EntityRelationshipRoles>
  </EntityRelationship>
  <EntityRelationship Name="crf46_gig_employee_onboarding_gig_reporting_manager_cr8b3_gw_employee_details">
    <EntityRelationshipType>OneToMany</EntityRelationshipType>
    <IsCustomizable>1</IsCustomizable>
    <IntroducedVersion>1.0.0.0</IntroducedVersion>
    <IsHierarchical>0</IsHierarchical>
    <ReferencingEntityName>crf46_gig_employee_onboarding</ReferencingEntityName>
    <ReferencedEntityName>cr8b3_gw_Employee_details</ReferencedEntityName>
    <CascadeAssign>NoCascade</CascadeAssign>
    <CascadeDelete>RemoveLink</CascadeDelete>
    <CascadeArchive>RemoveLink</CascadeArchive>
    <CascadeReparent>NoCascade</CascadeReparent>
    <CascadeShare>NoCascade</CascadeShare>
    <CascadeUnshare>NoCascade</CascadeUnshare>
    <CascadeRollupView>NoCascade</CascadeRollupView>
    <IsValidForAdvancedFind>1</IsValidForAdvancedFind>
    <ReferencingAttributeName>crf46_gig_reporting_manager</ReferencingAttributeName>
    <RelationshipDescription>
      <Descriptions>
        <Description description="" languagecode="1033" />
      </Descriptions>
    </RelationshipDescription>
    <EntityRelationshipRoles>
      <EntityRelationshipRole>
        <NavPaneDisplayOption>UseCollectionName</NavPaneDisplayOption>
        <NavPaneArea>Details</NavPaneArea>
        <NavPaneOrder>10000</NavPaneOrder>
        <NavigationPropertyName>crf46_gig_reporting_manager</NavigationPropertyName>
        <RelationshipRoleType>1</RelationshipRoleType>
      </EntityRelationshipRole>
      <EntityRelationshipRole>
        <NavigationPropertyName>crf46_gig_employee_onboarding_gig_reporting_manager_cr8b3_gw_employee_details</NavigationPropertyName>
        <RelationshipRoleType>0</RelationshipRoleType>
      </EntityRelationshipRole>
    </EntityRelationshipRoles>
  </EntityRelationship>
  <EntityRelationship Name="crf46_gig_salary_statement_gig_employee_code_cr8b3_gw_employee_details">
    <EntityRelationshipType>OneToMany</EntityRelationshipType>
    <IsCustomizable>1</IsCustomizable>
    <IntroducedVersion>1.0.0.0</IntroducedVersion>
    <IsHierarchical>0</IsHierarchical>
    <ReferencingEntityName>crf46_gig_salary_statement</ReferencingEntityName>
    <ReferencedEntityName>cr8b3_gw_Employee_details</ReferencedEntityName>
    <CascadeAssign>NoCascade</CascadeAssign>
    <CascadeDelete>RemoveLink</CascadeDelete>
    <CascadeArchive>RemoveLink</CascadeArchive>
    <CascadeReparent>NoCascade</CascadeReparent>
    <CascadeShare>NoCascade</CascadeShare>
    <CascadeUnshare>NoCascade</CascadeUnshare>
    <CascadeRollupView>NoCascade</CascadeRollupView>
    <IsValidForAdvancedFind>1</IsValidForAdvancedFind>
    <ReferencingAttributeName>crf46_gig_employee_code</ReferencingAttributeName>
    <RelationshipDescription>
      <Descriptions>
        <Description description="" languagecode="1033" />
      </Descriptions>
    </RelationshipDescription>
    <EntityRelationshipRoles>
      <EntityRelationshipRole>
        <NavPaneDisplayOption>UseCollectionName</NavPaneDisplayOption>
        <NavPaneArea>Details</NavPaneArea>
        <NavPaneOrder>10000</NavPaneOrder>
        <NavigationPropertyName>crf46_gig_employee_code</NavigationPropertyName>
        <RelationshipRoleType>1</RelationshipRoleType>
      </EntityRelationshipRole>
      <EntityRelationshipRole>
        <NavigationPropertyName>crf46_gig_salary_statement_gig_employee_code_cr8b3_gw_employee_details</NavigationPropertyName>
        <RelationshipRoleType>0</RelationshipRoleType>
      </EntityRelationshipRole>
    </EntityRelationshipRoles>
  </EntityRelationship>
  <EntityRelationship Name="crf46_realignment_logs_employee_id_cr8b3_gw_employee_details">
    <EntityRelationshipType>OneToMany</EntityRelationshipType>
    <IsCustomizable>1</IsCustomizable>
    <IntroducedVersion>1.0.0.0</IntroducedVersion>
    <IsHierarchical>0</IsHierarchical>
    <ReferencingEntityName>crf46_realignment_logs</ReferencingEntityName>
    <ReferencedEntityName>cr8b3_gw_Employee_details</ReferencedEntityName>
    <CascadeAssign>NoCascade</CascadeAssign>
    <CascadeDelete>RemoveLink</CascadeDelete>
    <CascadeArchive>RemoveLink</CascadeArchive>
    <CascadeReparent>NoCascade</CascadeReparent>
    <CascadeShare>NoCascade</CascadeShare>
    <CascadeUnshare>NoCascade</CascadeUnshare>
    <CascadeRollupView>NoCascade</CascadeRollupView>
    <IsValidForAdvancedFind>1</IsValidForAdvancedFind>
    <ReferencingAttributeName>crf46_employee_id</ReferencingAttributeName>
    <RelationshipDescription>
      <Descriptions>
        <Description description="" languagecode="1033" />
      </Descriptions>
    </RelationshipDescription>
    <EntityRelationshipRoles>
      <EntityRelationshipRole>
        <NavPaneDisplayOption>UseCollectionName</NavPaneDisplayOption>
        <NavPaneArea>Details</NavPaneArea>
        <NavPaneOrder>10000</NavPaneOrder>
        <NavigationPropertyName>crf46_employee_id</NavigationPropertyName>
        <RelationshipRoleType>1</RelationshipRoleType>
      </EntityRelationshipRole>
      <EntityRelationshipRole>
        <NavigationPropertyName>crf46_realignment_logs_employee_id_cr8b3_gw_employee_details</NavigationPropertyName>
        <RelationshipRoleType>0</RelationshipRoleType>
      </EntityRelationshipRole>
    </EntityRelationshipRoles>
  </EntityRelationship>
</EntityRelationships>